[
    {
        "id": 1,
        "name": "FULL WINTER KIT",
        "price": 100,
        "image": "https://i.ibb.co/kq8p04P/home-Product.png",
        "shortDes": "Half Jacket + Skinny Trouser + Boot lether",
        "moreImage": [
            "https://i.ibb.co/kq8p04P/home-Product.png",
            "https://i.ibb.co/ct6n2QV/hat.png",
            "https://i.ibb.co/d4XG8Qq/Trouser.png"
        ],
        "sizes": [
            "s",
            "l",
            "xl"
        ],
        "color": [
            "red",
            "blue",
            "green"
        ],
        "Brand": "Reebok",
        "des": "lorem ipsum dummy text goes here.lorem ipsum dummy text goes herelorem ipsum dummy text goes herelorem ipsum dummy text goes here"
    },
    {
        "id": 2,
        "name": "One Man Shirt Red One Man Shirt Red One Man Shirt Red",
        "price": 120,
        "image": "https://i.ibb.co/RPbtcTw/Product2.png",
        "moreImage": [
            "https://i.ibb.co/RPbtcTw/Product2.png",
            "https://i.ibb.co/ct6n2QV/hat.png",
            "https://i.ibb.co/d4XG8Qq/Trouser.png"
        ],
        "sizes": [
            "s",
            "m"
        ],
        "color": [
            "red",
            "yellow",
            "green"
        ],
        "Brand": "Addidas",
        "shortDes": "Jacket + Skinny Pant + lether",
        "des": "lorem ipsum dummy text goes here.lorem ipsum dummy text goes herelorem ipsum dummy text goes herelorem ipsum dummy text goes here"
    },
    {
        "id": 3,
        "name": "Jacket Track Reebok",
        "price": 200,
        "image": "https://i.ibb.co/kq8p04P/home-Product.png",
        "moreImage": [
            "https://i.ibb.co/kq8p04P/home-Product.png",
            "https://i.ibb.co/ct6n2QV/hat.png",
            "https://i.ibb.co/d4XG8Qq/Trouser.png"
        ],
        "sizes": [
            "l",
            "xl"
        ],
        "color": [
            "red",
            "pink",
            "green"
        ],
        "Brand": "Nike",
        "shortDes": "Special Cotton + Export Quality",
        "des": "lorem ipsum dummy text goes here.lorem ipsum dummy text goes herelorem ipsum dummy text goes herelorem ipsum dummy text goes here"
    },
    {
        "id": 4,
        "name": "Reebok Track Jacket",
        "price": 150,
        "image": "https://i.ibb.co/xXSSxFr/Product4.png",
        "moreImage": [
            "https://i.ibb.co/xXSSxFr/Product4.png",
            "https://i.ibb.co/ct6n2QV/hat.png",
            "https://i.ibb.co/d4XG8Qq/Trouser.png"
        ],
        "sizes": [
            "s",
            "xl"
        ],
        "color": [
            "red",
            "yellow",
            "green"
        ],
        "Brand": "Addidas",
        "shortDes": "Half Jacket + Skinny Trouser + Boot lether",
        "des": "lorem ipsum dummy text goes here.lorem ipsum dummy text goes herelorem ipsum dummy text goes herelorem ipsum dummy text goes here"
    },
    {
        "id": 5,
        "name": "Reebok Track Jacket",
        "price": 180,
        "image": "https://i.ibb.co/xXSSxFr/Product4.png",
        "shortDes": "Half Jacket + Skinny Trouser + Boot lether",
        "moreImage": [
            "https://i.ibb.co/kq8p04P/home-Product.png",
            "https://i.ibb.co/ct6n2QV/hat.png",
            "https://i.ibb.co/d4XG8Qq/Trouser.png"
        ],
        "sizes": [
            "s",
            "m",
            "xl"
        ],
        "color": [
            "red",
            "blue",
            "green"
        ],
        "Brand": "Nike",
        "des": "lorem ipsum dummy text goes here.lorem ipsum dummy text goes herelorem ipsum dummy text goes herelorem ipsum dummy text goes here"
    },
    {
        "id": 6,
        "name": "Reebok Track Jacket",
        "price": 200,
        "image": "https://i.ibb.co/kq8p04P/home-Product.png",
        "moreImage": [
            "https://i.ibb.co/RPbtcTw/Product2.png",
            "https://i.ibb.co/ct6n2QV/hat.png",
            "https://i.ibb.co/d4XG8Qq/Trouser.png"
        ],
        "sizes": [
            "s"
        ],
        "color": [
            "red",
            "yellow",
            "green"
        ],
        "Brand": "Reebok",
        "shortDes": "Half Jacket + Skinny Trouser + Boot lether",
        "des": "lorem ipsum dummy text goes here.lorem ipsum dummy text goes herelorem ipsum dummy text goes herelorem ipsum dummy text goes here"
    },
    {
        "id": 7,
        "name": "Reebok Track Jacket",
        "price": 170,
        "image": "https://i.ibb.co/RPbtcTw/Product2.png",
        "moreImage": [
            "https://i.ibb.co/kq8p04P/home-Product.png",
            "https://i.ibb.co/ct6n2QV/hat.png",
            "https://i.ibb.co/d4XG8Qq/Trouser.png"
        ],
        "sizes": [
            "l",
            "xl"
        ],
        "color": [
            "red",
            "pink",
            "green"
        ],
        "Brand": "Nike",
        "shortDes": "Half Jacket + Skinny Trouser + Boot lether",
        "des": "lorem ipsum dummy text goes here.lorem ipsum dummy text goes herelorem ipsum dummy text goes herelorem ipsum dummy text goes here"
    },
    {
        "id": 8,
        "name": "Reebok Track Jacket",
        "price": 230,
        "image": "https://i.ibb.co/RPbtcTw/Product2.png",
        "moreImage": [
            "https://i.ibb.co/xXSSxFr/Product4.png",
            "https://i.ibb.co/ct6n2QV/hat.png",
            "https://i.ibb.co/d4XG8Qq/Trouser.png"
        ],
        "sizes": [
            "xl"
        ],
        "color": [
            "red",
            "yellow",
            "green"
        ],
        "Brand": "Active",
        "shortDes": "Half Jacket + Skinny Trouser + Boot lether",
        "des": "lorem ipsum dummy text goes here.lorem ipsum dummy text goes herelorem ipsum dummy text goes herelorem ipsum dummy text goes here"
    },
    {
        "id": 9,
        "name": "Reebok Track Jacket",
        "price": 180,
        "image": "https://i.ibb.co/kq8p04P/home-Product.png",
        "moreImage": [
            "https://i.ibb.co/RPbtcTw/Product2.png",
            "https://i.ibb.co/ct6n2QV/hat.png",
            "https://i.ibb.co/d4XG8Qq/Trouser.png"
        ],
        "sizes": [
            "s",
            "m",
            "xl"
        ],
        "color": [
            "red",
            "yellow",
            "green"
        ],
        "Brand": "Reebok",
        "shortDes": "Half Jacket + Skinny Trouser + Boot lether",
        "des": "lorem ipsum dummy text goes here.lorem ipsum dummy text goes herelorem ipsum dummy text goes herelorem ipsum dummy text goes here"
    },
    {
        "id": 10,
        "name": "Red-brown mans jacket",
        "price": 170,
        "image": "https://i.ibb.co/RPbtcTw/Product2.png",
        "shortDes": "Half Jacket + Skinny Trouser + Boot lether",
        "moreImage": [
            "https://i.ibb.co/kq8p04P/home-Product.png",
            "https://i.ibb.co/ct6n2QV/hat.png",
            "https://i.ibb.co/d4XG8Qq/Trouser.png"
        ],
        "sizes": [
            "s",
            "m",
            "l"
        ],
        "color": [
            "red",
            "blue",
            "green"
        ],
        "Brand": "Active",
        "des": "lorem ipsum dummy text goes here.lorem ipsum dummy text goes herelorem ipsum dummy text goes herelorem ipsum dummy text goes here"
    },
    {
        "id": 11,
        "name": "Reebok Track Jacket",
        "price": 220,
        "image": "https://i.ibb.co/d4XG8Qq/Trouser.png",
        "moreImage": [
            "https://i.ibb.co/xXSSxFr/Product4.png",
            "https://i.ibb.co/ct6n2QV/hat.png",
            "https://i.ibb.co/d4XG8Qq/Trouser.png"
        ],
        "sizes": [
            "s",
            "m",
            "l",
            "xl"
        ],
        "color": [
            "red",
            "yellow",
            "green"
        ],
        "Brand": "Addidas",
        "shortDes": "Half Jacket + Skinny Trouser + Boot lether",
        "des": "lorem ipsum dummy text goes here.lorem ipsum dummy text goes herelorem ipsum dummy text goes herelorem ipsum dummy text goes here"
    },
    {
        "id": 12,
        "name": "Reebok Track Jacket",
        "price": 160,
        "image": "https://i.ibb.co/qphbLP9/Product5.png",
        "moreImage": [
            "https://i.ibb.co/kq8p04P/home-Product.png",
            "https://i.ibb.co/ct6n2QV/hat.png",
            "https://i.ibb.co/d4XG8Qq/Trouser.png"
        ],
        "sizes": [
            "s",
            "xl"
        ],
        "color": [
            "red",
            "pink",
            "green"
        ],
        "Brand": "Active",
        "shortDes": "Half Jacket + Skinny Trouser + Boot lether",
        "des": "lorem ipsum dummy text goes here.lorem ipsum dummy text goes herelorem ipsum dummy text goes herelorem ipsum dummy text goes here"
    },
    {
        "id": 13,
        "name": "FULL WINTER KIT",
        "price": 130,
        "image": "https://i.ibb.co/cvCTYXL/Product-Show.png",
        "shortDes": "Half Jacket + Skinny Trouser + Boot lether",
        "moreImage": [
            "https://i.ibb.co/kq8p04P/home-Product.png",
            "https://i.ibb.co/ct6n2QV/hat.png",
            "https://i.ibb.co/d4XG8Qq/Trouser.png"
        ],
        "sizes": [
            "s",
            "l",
            "xl"
        ],
        "color": [
            "red",
            "blue",
            "green"
        ],
        "Brand": "Reebok",
        "des": "lorem ipsum dummy text goes here.lorem ipsum dummy text goes herelorem ipsum dummy text goes herelorem ipsum dummy text goes here"
    },
    {
        "id": 14,
        "name": "One Man Shirt Red",
        "price": 140,
        "image": "https://i.ibb.co/ct6n2QV/hat.png",
        "moreImage": [
            "https://i.ibb.co/ct6n2QV/hat.png",
            "https://i.ibb.co/ct6n2QV/hat.png",
            "https://i.ibb.co/d4XG8Qq/Trouser.png"
        ],
        "sizes": [
            "s",
            "m"
        ],
        "color": [
            "red",
            "yellow",
            "green"
        ],
        "Brand": "Addidas",
        "shortDes": "Jacket + Skinny Pant + lether",
        "des": "lorem ipsum dummy text goes here.lorem ipsum dummy text goes herelorem ipsum dummy text goes herelorem ipsum dummy text goes here"
    },
    {
        "id": 15,
        "name": "Jacket Track Reebok",
        "price": 150,
        "image": "https://i.ibb.co/FhBWH3y/writer4.png",
        "moreImage": [
            "https://i.ibb.co/FhBWH3y/writer4.png",
            "https://i.ibb.co/ct6n2QV/hat.png",
            "https://i.ibb.co/d4XG8Qq/Trouser.png"
        ],
        "sizes": [
            "l",
            "xl"
        ],
        "color": [
            "red",
            "pink",
            "green"
        ],
        "Brand": "Nike",
        "shortDes": "Special Cotton + Export Quality",
        "des": "lorem ipsum dummy text goes here.lorem ipsum dummy text goes herelorem ipsum dummy text goes herelorem ipsum dummy text goes here"
    },
    {
        "id": 16,
        "name": "Reebok Track Jacket",
        "price": 160,
        "image": "https://i.ibb.co/Bj2T1ty/cycle8.jpg",
        "moreImage": [
            "https://i.ibb.co/Bj2T1ty/cycle8.jpg",
            "https://i.ibb.co/ct6n2QV/hat.png",
            "https://i.ibb.co/d4XG8Qq/Trouser.png"
        ],
        "sizes": [
            "s",
            "xl"
        ],
        "color": [
            "red",
            "yellow",
            "green"
        ],
        "Brand": "Addidas",
        "shortDes": "Half Jacket + Skinny Trouser + Boot lether",
        "des": "lorem ipsum dummy text goes here.lorem ipsum dummy text goes herelorem ipsum dummy text goes herelorem ipsum dummy text goes here"
    },
    {
        "id": 17,
        "name": "Reebok Track Jacket",
        "price": 170,
        "image": "https://i.ibb.co/2gfHfm3/cycle2.jpg",
        "shortDes": "Half Jacket + Skinny Trouser + Boot lether",
        "moreImage": [
            "https://i.ibb.co/kq8p04P/home-Product.png",
            "https://i.ibb.co/ct6n2QV/hat.png",
            "https://i.ibb.co/d4XG8Qq/Trouser.png"
        ],
        "sizes": [
            "s",
            "m",
            "xl"
        ],
        "color": [
            "red",
            "blue",
            "green"
        ],
        "Brand": "Nike",
        "des": "lorem ipsum dummy text goes here.lorem ipsum dummy text goes herelorem ipsum dummy text goes herelorem ipsum dummy text goes here"
    },
    {
        "id": 18,
        "name": "Reebok Track Jacket",
        "price": 180,
        "image": "https://i.ibb.co/3d0x7X9/room1-1.jpg",
        "moreImage": [
            "https://i.ibb.co/RPbtcTw/Product2.png",
            "https://i.ibb.co/ct6n2QV/hat.png",
            "https://i.ibb.co/d4XG8Qq/Trouser.png"
        ],
        "sizes": [
            "s"
        ],
        "color": [
            "red",
            "yellow",
            "green"
        ],
        "Brand": "Reebok",
        "shortDes": "Half Jacket + Skinny Trouser + Boot lether",
        "des": "lorem ipsum dummy text goes here.lorem ipsum dummy text goes herelorem ipsum dummy text goes herelorem ipsum dummy text goes here"
    },
    {
        "id": 19,
        "name": "Reebok Track Jacket",
        "price": 190,
        "image": "https://i.ibb.co/3v5S1Qf/cycle7.jpg",
        "moreImage": [
            "https://i.ibb.co/kq8p04P/home-Product.png",
            "https://i.ibb.co/ct6n2QV/hat.png",
            "https://i.ibb.co/d4XG8Qq/Trouser.png"
        ],
        "sizes": [
            "l",
            "xl"
        ],
        "color": [
            "red",
            "pink",
            "green"
        ],
        "Brand": "Nike",
        "shortDes": "Half Jacket + Skinny Trouser + Boot lether",
        "des": "lorem ipsum dummy text goes here.lorem ipsum dummy text goes herelorem ipsum dummy text goes herelorem ipsum dummy text goes here"
    },
    {
        "id": 20,
        "name": "Reebok Track Jacket",
        "price": 200,
        "image": "https://i.ibb.co/kSt6Ks6/room6-1.jpg",
        "moreImage": [
            "https://i.ibb.co/xXSSxFr/Product4.png",
            "https://i.ibb.co/ct6n2QV/hat.png",
            "https://i.ibb.co/d4XG8Qq/Trouser.png"
        ],
        "sizes": [
            "xl"
        ],
        "color": [
            "red",
            "yellow",
            "green"
        ],
        "Brand": "Active",
        "shortDes": "Half Jacket + Skinny Trouser + Boot lether",
        "des": "lorem ipsum dummy text goes here.lorem ipsum dummy text goes herelorem ipsum dummy text goes herelorem ipsum dummy text goes here"
    },
    {
        "id": 21,
        "name": "Reebok Track Jacket",
        "price": 210,
        "image": "https://i.ibb.co/pdCSzMv/image.jpg",
        "moreImage": [
            "https://i.ibb.co/RPbtcTw/Product2.png",
            "https://i.ibb.co/ct6n2QV/hat.png",
            "https://i.ibb.co/d4XG8Qq/Trouser.png"
        ],
        "sizes": [
            "s",
            "m",
            "xl"
        ],
        "color": [
            "red",
            "yellow",
            "green"
        ],
        "Brand": "Reebok",
        "shortDes": "Half Jacket + Skinny Trouser + Boot lether",
        "des": "lorem ipsum dummy text goes here.lorem ipsum dummy text goes herelorem ipsum dummy text goes herelorem ipsum dummy text goes here"
    },
    {
        "id": 22,
        "name": "Red-brown mans jacket",
        "price": 220,
        "image": "https://i.ibb.co/xXSSxFr/Product4.png",
        "shortDes": "Half Jacket + Skinny Trouser + Boot lether",
        "moreImage": [
            "https://i.ibb.co/kq8p04P/home-Product.png",
            "https://i.ibb.co/ct6n2QV/hat.png",
            "https://i.ibb.co/d4XG8Qq/Trouser.png"
        ],
        "sizes": [
            "s",
            "m",
            "l"
        ],
        "color": [
            "red",
            "blue",
            "green"
        ],
        "Brand": "Active",
        "des": "lorem ipsum dummy text goes here.lorem ipsum dummy text goes herelorem ipsum dummy text goes herelorem ipsum dummy text goes here"
    },
    {
        "id": 23,
        "name": "Reebok Track Jacket",
        "price": 210,
        "image": "https://i.ibb.co/LksmT9J/room9-1.jpg",
        "moreImage": [
            "https://i.ibb.co/xXSSxFr/Product4.png",
            "https://i.ibb.co/ct6n2QV/hat.png",
            "https://i.ibb.co/d4XG8Qq/Trouser.png"
        ],
        "sizes": [
            "s",
            "m",
            "l",
            "xl"
        ],
        "color": [
            "red",
            "yellow",
            "green"
        ],
        "Brand": "Addidas",
        "shortDes": "Half Jacket + Skinny Trouser + Boot lether",
        "des": "lorem ipsum dummy text goes here.lorem ipsum dummy text goes herelorem ipsum dummy text goes herelorem ipsum dummy text goes here"
    },
    {
        "id": 24,
        "name": "Reebok Track Jacket",
        "price": 90,
        "image": "https://i.ibb.co/xXSSxFr/Product4.png",
        "moreImage": [
            "https://i.ibb.co/kq8p04P/home-Product.png",
            "https://i.ibb.co/ct6n2QV/hat.png",
            "https://i.ibb.co/d4XG8Qq/Trouser.png"
        ],
        "sizes": [
            "s",
            "xl"
        ],
        "color": [
            "red",
            "pink",
            "green"
        ],
        "Brand": "Active",
        "shortDes": "Half Jacket + Skinny Trouser + Boot lether",
        "des": "lorem ipsum dummy text goes here.lorem ipsum dummy text goes herelorem ipsum dummy text goes herelorem ipsum dummy text goes here"
    },
    {
        "id": 25,
        "name": "Reebok Track Jacket",
        "price": 210,
        "image": "https://i.ibb.co/RPbtcTw/Product2.png",
        "moreImage": [
            "https://i.ibb.co/xXSSxFr/Product4.png",
            "https://i.ibb.co/ct6n2QV/hat.png",
            "https://i.ibb.co/d4XG8Qq/Trouser.png"
        ],
        "sizes": [
            "s",
            "m",
            "l",
            "xl"
        ],
        "color": [
            "red",
            "yellow",
            "green"
        ],
        "Brand": "Addidas",
        "shortDes": "Half Jacket + Skinny Trouser + Boot lether",
        "des": "lorem ipsum dummy text goes here.lorem ipsum dummy text goes herelorem ipsum dummy text goes herelorem ipsum dummy text goes here"
    },
    {
        "id": 26,
        "name": "Reebok Track Jacket",
        "price": 90,
        "image": "https://i.ibb.co/xXSSxFr/Product4.png",
        "moreImage": [
            "https://i.ibb.co/kq8p04P/home-Product.png",
            "https://i.ibb.co/ct6n2QV/hat.png",
            "https://i.ibb.co/d4XG8Qq/Trouser.png"
        ],
        "sizes": [
            "s",
            "xl"
        ],
        "color": [
            "red",
            "pink",
            "green"
        ],
        "Brand": "Active",
        "shortDes": "Half Jacket + Skinny Trouser + Boot lether",
        "des": "lorem ipsum dummy text goes here.lorem ipsum dummy text goes herelorem ipsum dummy text goes herelorem ipsum dummy text goes here"
    }
]